mmar_llm/__init__.py
mmar_llm/airi_endpoint.py
mmar_llm/dummy_endpoint.py
mmar_llm/endpoints.py
mmar_llm/fusion_brain_endpoint.py
mmar_llm/gigachat_endpoint.py
mmar_llm/io_sugar.py
mmar_llm/llm_endpoint.py
mmar_llm/llm_hub.py
mmar_llm/llm_hub_config.py
mmar_llm/models.py
mmar_llm/openrouter_endpoint.py
mmar_llm/py.typed
mmar_llm/utils.py
mmar_llm/yandex_gpt_endpoint.py
mmar_llm-2.0.13.dist-info/licenses/LICENSE
mmar_llm-2.0.13.dist-info/WHEEL
mmar_llm-2.0.13.dist-info/METADATA
mmar_llm-2.0.13.dist-info/RECORD
