Metadata-Version: 2.4
Name: mmar-llm
Version: 2.0.13
Summary: llm wrappers for multimodal architectures team
Keywords: 
Author: Eugene Tagin
Author-email: Eugene Tagin <tagin@airi.net>
License-Expression: MIT
License-File: LICENSE
Classifier: Development Status :: 4 - Beta
Classifier: Intended Audience :: Developers
Classifier: Programming Language :: Python
Classifier: Programming Language :: Python :: 3
Classifier: Programming Language :: Python :: 3 :: Only
Classifier: Programming Language :: Python :: 3.11
Classifier: Programming Language :: Python :: 3.12
Classifier: Programming Language :: Python :: 3.13
Classifier: Programming Language :: Python :: 3.14
Classifier: Topic :: Documentation
Classifier: Topic :: Software Development
Classifier: Topic :: Utilities
Classifier: Typing :: Typed
Requires-Dist: requests~=2.32.5
Requires-Dist: gigachat==0.1.43
Requires-Dist: tiktoken==0.8.0
Requires-Dist: openai>=1.61.0
Requires-Dist: loguru~=0.7.3
Requires-Dist: mmar-mapi~=1.4.2
Requires-Dist: mmar-utils~=1.1.15
Requires-Python: >=3.11
